setup.py
wavefront-collector
wf
test/test_system_checker.py
wavefront/__init__.py
wavefront/appdynamics.py
wavefront/aws_common.py
wavefront/awsbilling.py
wavefront/awscloudwatch.py
wavefront/awsmetrics.py
wavefront/command.py
wavefront/metrics_writer.py
wavefront/newrelic.py
wavefront/newrelic_common.py
wavefront/system_checker.py
wavefront/utils.py
wavefront_collector.egg-info/PKG-INFO
wavefront_collector.egg-info/SOURCES.txt
wavefront_collector.egg-info/dependency_links.txt
wavefront_collector.egg-info/requires.txt
wavefront_collector.egg-info/top_level.txt