Metadata-Version: 1.1
Name: wavefront-collector
Version: 0.0.49
Summary: Wavefront Collector Tools
Home-page: https://www.wavefront.com
Author: Wavefront
Author-email: mike@wavefront.com
License: BSD
Keywords: wavefront wavefront_integration collector metrics
Platform: UNKNOWN
Classifier: Development Status :: 4 - Beta
Classifier: Topic :: Utilities
Classifier: License :: OSI Approved :: BSD License
